setup.py
src/django_boreas.egg-info/PKG-INFO
src/django_boreas.egg-info/SOURCES.txt
src/django_boreas.egg-info/dependency_links.txt
src/django_boreas.egg-info/requires.txt
src/django_boreas.egg-info/top_level.txt
src/djboreas/__init__.py
src/djboreas/models.py
src/djboreas/management/__init__.py
src/djboreas/management/commands/__init__.py
src/djboreas/management/commands/djboreas.py