Metadata-Version: 1.0
Name: django-boreas
Version: 0.1
Summary: Django management commands for boreas
Home-page: http://django.boreas.readthedocs.org/
Author: Karol Majta
Author-email: karol@karolmajta.com
License: JSON License
Keywords: websocket pub sub pubsub boreas django
Platform: UNKNOWN
